loki/__init__.py
loki/cli.py
loki/commands/__init__.py
loki/commands/csv.py
loki/commands/json.py
loki/commands/jwt.py
loki/commands/saml.py
loki/commands/xml.py
loki/commands/yaml.py
loki_cli-0.1.0.dist-info/licenses/LICENSE
loki_cli-0.1.0.dist-info/METADATA
loki_cli-0.1.0.dist-info/WHEEL
loki_cli-0.1.0.dist-info/entry_points.txt
loki_cli-0.1.0.dist-info/top_level.txt
loki_cli-0.1.0.dist-info/RECORD
