Metadata-Version: 2.4
Name: loki-cli
Version: 0.1.0
Summary: Offline Developer CLI for data transformation, formatting, and token decoding
Author: Loki Project Developers
License: MIT License
Project-URL: Homepage, https://github.com/code-chaios/loki
Project-URL: Repository, https://github.com/code-chaios/loki.git
Classifier: Development Status :: 4 - Beta
Classifier: Intended Audience :: Developers
Classifier: License :: OSI Approved :: MIT License
Classifier: Programming Language :: Python :: 3
Classifier: Programming Language :: Python :: 3.9
Classifier: Programming Language :: Python :: 3.10
Classifier: Programming Language :: Python :: 3.11
Classifier: Programming Language :: Python :: 3.12
Classifier: Topic :: Software Development :: Libraries :: Python Modules
Classifier: Topic :: Text Processing :: Markup
Classifier: Topic :: Text Processing :: Markup :: XML
Classifier: Topic :: Utilities
Requires-Python: >=3.9
License-File: LICENSE
Requires-Dist: typer>=0.9.0
Requires-Dist: pyjwt>=2.8.0
Requires-Dist: python3-saml>=1.15.0
Requires-Dist: pyyaml>=6.0.1
Requires-Dist: lxml>=4.9.3
Requires-Dist: pandas>=2.0.3
Provides-Extra: test
Requires-Dist: pytest>=7.4.0; extra == "test"
Requires-Dist: pytest-cov>=4.1.0; extra == "test"
Dynamic: license-file
